{"output1": {"prdy_vrss": "300", "prdy_vrss_sign": "2", "prdy_ctrt": "0.25", "stck_prdy_clpr": "118200", "acml_vol": "2893352", "acml_tr_pbmn": "342956336900", "hts_kor_isnm": "SK\ud558\uc774\ub2c9\uc2a4", "stck_prpr": "118500", "stck_shrn_iscd": "000660", "prdy_vol": "1615519", "stck_mxpr": "153600", "stck_llam": "82800", "stck_oprc": "118200", "stck_hgpr": "120900", "stck_lwpr": "117100", "stck_prdy_oprc": "118600", "stck_prdy_hgpr": "120000", "stck_prdy_lwpr": "117800", "askp": "118500", "bidp": "118400", "prdy_vrss_vol": "1277833", "vol_tnrt": "0.40", "stck_fcam": "5000", "lstn_stcn": "728002365", "cpfn": "36577", "hts_avls": "862683", "per": "38.69", "eps": "3063.00", "pbr": "1.32", "itewhol_loan_rmnd_ratem name": "0.21"}, "output2": [{"stck_bsop_date": "20230907", "stck_clpr": "118500", "stck_oprc": "118200", "stck_hgpr": "120900", "stck_lwpr": "117100", "acml_vol": "2893352", "acml_tr_pbmn": "342956336900", "flng_cls_code": "00", "prtt_rate": "0.00", "mod_yn": "N", "prdy_vrss_sign": "2", "prdy_vrss": "300", "revl_issu_reas": ""}, {"stck_bsop_date": "20230906", "stck_clpr": "118200", "stck_oprc": "118600", "stck_hgpr": "120000", "stck_lwpr": "117800", "acml_vol": "1615519", "acml_tr_pbmn": "191335016200", "flng_cls_code": "00", "prtt_rate": "0.00", "mod_yn": "N", "prdy_vrss_sign": "5", "prdy_vrss": "-1200", "revl_issu_reas": ""}, {"stck_bsop_date": "20230905", "stck_clpr": "119400", "stck_oprc": "118100", "stck_hgpr": "121000", "stck_lwpr": "117700", "acml_vol": "1749591", "acml_tr_pbmn": "209186512876", "flng_cls_code": "00", "prtt_rate": "0.00", "mod_yn": "N", "prdy_vrss_sign": "2", "prdy_vrss": "200", "revl_issu_reas": ""}, {"stck_bsop_date": "20230904", "stck_clpr": "119200", "stck_oprc": "118300", "stck_hgpr": "119700", "stck_lwpr": "116200", "acml_vol": "3491280", "acml_tr_pbmn": "410802524712", "flng_cls_code": "00", "prtt_rate": "0.00", "mod_yn": "N", "prdy_vrss_sign": "5", "prdy_vrss": "-800", "revl_issu_reas": ""}, {"stck_bsop_date": "20230901", "stck_clpr": "120000", "stck_oprc": "121400", "stck_hgpr": "122600", "stck_lwpr": "119600", "acml_vol": "2886011", "acml_tr_pbmn": "349554847550", "flng_cls_code": "00", "prtt_rate": "0.00", "mod_yn": "N", "prdy_vrss_sign": "5", "prdy_vrss": "-1800", "revl_issu_reas": ""}, {"stck_bsop_date": "20230831", "stck_clpr": "121800", "stck_oprc": "121000", "stck_hgpr": "122800", "stck_lwpr": "120000", "acml_vol": "4403695", "acml_tr_pbmn": "536628688400", "flng_cls_code": "00", "prtt_rate": "0.00", "mod_yn": "N", "prdy_vrss_sign": "2", "prdy_vrss": "2400", "revl_issu_reas": ""}, {"stck_bsop_date": "20230830", "stck_clpr": "119400", "stck_oprc": "122400", "stck_hgpr": "122800", "stck_lwpr": "119400", "acml_vol": "2629711", "acml_tr_pbmn": "318483532000", "flng_cls_code": "00", "prtt_rate": "0.00", "mod_yn": "N", "prdy_vrss_sign": "2", "prdy_vrss": "800", "revl_issu_reas": ""}], "rt_cd": "0", "msg_cd": "MCA00000", "msg1": "\uc815\uc0c1\ucc98\ub9ac \ub418\uc5c8\uc2b5\ub2c8\ub2e4."}